[
    {
        "inputs": [
            {
                "internalType": "contract Unirep",
                "name": "_unirep",
                "type": "address"
            },
            {
                "internalType": "contract EpochKeyVerifierHelper",
                "name": "_epkHelper",
                "type": "address"
            },
            {
                "internalType": "contract EpochKeyLiteVerifierHelper",
                "name": "_epkLiteHelper",
                "type": "address"
            },
            {
                "internalType": "contract IVerifier",
                "name": "_dataVerifier",
                "type": "address"
            },
            {
                "internalType": "contract VerifierHelperManager",
                "name": "_verifierHelperManager",
                "type": "address"
            },
            {
                "internalType": "uint48",
                "name": "_epochLength",
                "type": "uint48"
            }
        ],
        "stateMutability": "nonpayable",
        "type": "constructor"
    },
    { "inputs": [], "name": "ArrMismatch", "type": "error" },
    { "inputs": [], "name": "InvalidAttester", "type": "error" },
    {
        "inputs": [
            { "internalType": "uint256", "name": "epochKey", "type": "uint256" }
        ],
        "name": "InvalidCommentEpochKey",
        "type": "error"
    },
    {
        "inputs": [
            {
                "internalType": "uint256",
                "name": "commentId",
                "type": "uint256"
            }
        ],
        "name": "InvalidCommentId",
        "type": "error"
    },
    { "inputs": [], "name": "InvalidEpoch", "type": "error" },
    { "inputs": [], "name": "ProofHasUsed", "type": "error" },
    {
        "inputs": [
            {
                "internalType": "uint256",
                "name": "hashUserId",
                "type": "uint256"
            }
        ],
        "name": "UserHasRegistered",
        "type": "error"
    },
    {
        "anonymous": false,
        "inputs": [
            {
                "indexed": true,
                "internalType": "uint256",
                "name": "epochKey",
                "type": "uint256"
            },
            {
                "indexed": true,
                "internalType": "uint256",
                "name": "postId",
                "type": "uint256"
            },
            {
                "indexed": true,
                "internalType": "uint256",
                "name": "commentId",
                "type": "uint256"
            },
            {
                "indexed": false,
                "internalType": "uint256",
                "name": "epoch",
                "type": "uint256"
            },
            {
                "indexed": false,
                "internalType": "string",
                "name": "content",
                "type": "string"
            }
        ],
        "name": "Comment",
        "type": "event"
    },
    {
        "anonymous": false,
        "inputs": [
            {
                "indexed": true,
                "internalType": "uint256",
                "name": "epochKey",
                "type": "uint256"
            },
            {
                "indexed": true,
                "internalType": "uint256",
                "name": "postId",
                "type": "uint256"
            },
            {
                "indexed": true,
                "internalType": "uint256",
                "name": "epoch",
                "type": "uint256"
            },
            {
                "indexed": false,
                "internalType": "string",
                "name": "content",
                "type": "string"
            }
        ],
        "name": "Post",
        "type": "event"
    },
    {
        "anonymous": false,
        "inputs": [
            {
                "indexed": true,
                "internalType": "uint256",
                "name": "epochKey",
                "type": "uint256"
            },
            {
                "indexed": true,
                "internalType": "uint256",
                "name": "postId",
                "type": "uint256"
            },
            {
                "indexed": true,
                "internalType": "uint256",
                "name": "commentId",
                "type": "uint256"
            },
            {
                "indexed": false,
                "internalType": "uint256",
                "name": "epoch",
                "type": "uint256"
            },
            {
                "indexed": false,
                "internalType": "string",
                "name": "newContent",
                "type": "string"
            }
        ],
        "name": "UpdatedComment",
        "type": "event"
    },
    {
        "anonymous": false,
        "inputs": [
            {
                "indexed": true,
                "internalType": "uint256",
                "name": "hashUserId",
                "type": "uint256"
            },
            {
                "indexed": true,
                "internalType": "bool",
                "name": "fromServer",
                "type": "bool"
            }
        ],
        "name": "UserSignUp",
        "type": "event"
    },
    {
        "inputs": [
            {
                "internalType": "uint256[]",
                "name": "publicSignals",
                "type": "uint256[]"
            },
            {
                "internalType": "uint256[8]",
                "name": "proof",
                "type": "uint256[8]"
            },
            { "internalType": "uint256", "name": "postId", "type": "uint256" },
            {
                "internalType": "uint256",
                "name": "commentId",
                "type": "uint256"
            },
            { "internalType": "string", "name": "newContent", "type": "string" }
        ],
        "name": "editComment",
        "outputs": [],
        "stateMutability": "nonpayable",
        "type": "function"
    },
    {
        "inputs": [],
        "name": "latestPostId",
        "outputs": [
            { "internalType": "uint256", "name": "", "type": "uint256" }
        ],
        "stateMutability": "view",
        "type": "function"
    },
    {
        "inputs": [
            {
                "internalType": "uint256[]",
                "name": "publicSignals",
                "type": "uint256[]"
            },
            {
                "internalType": "uint256[8]",
                "name": "proof",
                "type": "uint256[8]"
            },
            { "internalType": "uint256", "name": "postId", "type": "uint256" },
            { "internalType": "string", "name": "content", "type": "string" }
        ],
        "name": "leaveComment",
        "outputs": [],
        "stateMutability": "nonpayable",
        "type": "function"
    },
    {
        "inputs": [
            {
                "internalType": "uint256[]",
                "name": "publicSignals",
                "type": "uint256[]"
            },
            {
                "internalType": "uint256[8]",
                "name": "proof",
                "type": "uint256[8]"
            },
            { "internalType": "string", "name": "content", "type": "string" }
        ],
        "name": "post",
        "outputs": [],
        "stateMutability": "nonpayable",
        "type": "function"
    },
    {
        "inputs": [
            { "internalType": "uint256", "name": "", "type": "uint256" }
        ],
        "name": "postCommentIndex",
        "outputs": [
            { "internalType": "uint256", "name": "", "type": "uint256" }
        ],
        "stateMutability": "view",
        "type": "function"
    },
    {
        "inputs": [
            { "internalType": "bytes32", "name": "", "type": "bytes32" }
        ],
        "name": "proofNullifier",
        "outputs": [{ "internalType": "bool", "name": "", "type": "bool" }],
        "stateMutability": "view",
        "type": "function"
    },
    {
        "inputs": [
            {
                "internalType": "uint256",
                "name": "epochKey",
                "type": "uint256"
            },
            {
                "internalType": "uint48",
                "name": "targetEpoch",
                "type": "uint48"
            },
            {
                "internalType": "uint256",
                "name": "fieldIndex",
                "type": "uint256"
            },
            { "internalType": "uint256", "name": "val", "type": "uint256" }
        ],
        "name": "submitAttestation",
        "outputs": [],
        "stateMutability": "nonpayable",
        "type": "function"
    },
    {
        "inputs": [
            {
                "internalType": "uint256",
                "name": "epochKey",
                "type": "uint256"
            },
            {
                "internalType": "uint48",
                "name": "targetEpoch",
                "type": "uint48"
            },
            {
                "internalType": "uint256[]",
                "name": "fieldIndices",
                "type": "uint256[]"
            },
            { "internalType": "uint256[]", "name": "vals", "type": "uint256[]" }
        ],
        "name": "submitManyAttestations",
        "outputs": [],
        "stateMutability": "nonpayable",
        "type": "function"
    },
    {
        "inputs": [],
        "name": "unirep",
        "outputs": [
            { "internalType": "contract Unirep", "name": "", "type": "address" }
        ],
        "stateMutability": "view",
        "type": "function"
    },
    {
        "inputs": [
            { "internalType": "uint256", "name": "", "type": "uint256" }
        ],
        "name": "userRegistry",
        "outputs": [{ "internalType": "bool", "name": "", "type": "bool" }],
        "stateMutability": "view",
        "type": "function"
    },
    {
        "inputs": [
            {
                "internalType": "uint256[]",
                "name": "publicSignals",
                "type": "uint256[]"
            },
            {
                "internalType": "uint256[8]",
                "name": "proof",
                "type": "uint256[8]"
            },
            {
                "internalType": "uint256",
                "name": "hashUserId",
                "type": "uint256"
            },
            { "internalType": "bool", "name": "fromServer", "type": "bool" }
        ],
        "name": "userSignUp",
        "outputs": [],
        "stateMutability": "nonpayable",
        "type": "function"
    },
    {
        "inputs": [
            {
                "internalType": "uint256[7]",
                "name": "publicSignals",
                "type": "uint256[7]"
            },
            {
                "internalType": "uint256[8]",
                "name": "proof",
                "type": "uint256[8]"
            }
        ],
        "name": "verifyDataProof",
        "outputs": [{ "internalType": "bool", "name": "", "type": "bool" }],
        "stateMutability": "view",
        "type": "function"
    }
]
